piecad_viewer/__init__.py
piecad_viewer/server.py
piecad_viewer-1.0.0.dist-info/entry_points.txt
piecad_viewer-1.0.0.dist-info/LICENSE
piecad_viewer-1.0.0.dist-info/WHEEL
piecad_viewer-1.0.0.dist-info/METADATA
piecad_viewer-1.0.0.dist-info/RECORD
