Metadata-Version: 2.1
Name: piecad_viewer
Version: 1.0.0
Summary: "Viewer for Easy as Pie" CAD (Piecad)
Author-email: Brian Sturgill <codersnext@gmail.com>
Classifier: License :: OSI Approved :: MIT License
Requires-Dist: pyglet == 1.5.31
Requires-Dist: trimesh >= 1.26.4
Requires-Dist: glooey >= 0.3.6
Requires-Dist: scipy >= 1.15.2
Project-URL: Home, https://github.com/briansturgill/Piecad-Viewer
